{
	"$schema": "../package/core/schemas/theme.schema.json",
	"name": "Minimal",
	"author": "Om Mishra",
	"version": "1.0.0",
	"description": "Clean, understated UI sounds with short envelopes and low gain — subtle feedback that stays out of the way",
	"sounds": {
		"success": {
			"source": { "type": "sine", "frequency": 880 },
			"envelope": { "attack": 0, "decay": 0.08, "sustain": 0, "release": 0.02 },
			"gain": 0.08
		},
		"error": {
			"source": { "type": "sine", "frequency": { "start": 400, "end": 200 } },
			"envelope": { "attack": 0, "decay": 0.1, "sustain": 0, "release": 0.03 },
			"gain": 0.09
		},
		"warning": {
			"source": { "type": "sine", "frequency": 660 },
			"envelope": { "attack": 0, "decay": 0.06, "sustain": 0, "release": 0.02 },
			"gain": 0.07
		},
		"info": {
			"source": { "type": "sine", "frequency": 1100 },
			"envelope": {
				"attack": 0,
				"decay": 0.05,
				"sustain": 0,
				"release": 0.015
			},
			"gain": 0.06
		},
		"click": {
			"source": { "type": "sine", "frequency": 1200 },
			"envelope": {
				"attack": 0,
				"decay": 0.012,
				"sustain": 0,
				"release": 0.004
			},
			"gain": 0.1
		},
		"back": {
			"source": { "type": "sine", "frequency": { "start": 800, "end": 600 } },
			"envelope": {
				"attack": 0,
				"decay": 0.05,
				"sustain": 0,
				"release": 0.015
			},
			"gain": 0.08
		},
		"enter": {
			"source": { "type": "sine", "frequency": { "start": 600, "end": 900 } },
			"envelope": {
				"attack": 0,
				"decay": 0.05,
				"sustain": 0,
				"release": 0.015
			},
			"gain": 0.09
		},
		"delete": {
			"source": { "type": "sine", "frequency": { "start": 500, "end": 250 } },
			"envelope": {
				"attack": 0,
				"decay": 0.08,
				"sustain": 0,
				"release": 0.025
			},
			"gain": 0.08
		},
		"copy": {
			"source": { "type": "sine", "frequency": 1400 },
			"envelope": {
				"attack": 0,
				"decay": 0.01,
				"sustain": 0,
				"release": 0.004
			},
			"gain": 0.07
		},
		"paste": {
			"source": { "type": "sine", "frequency": 1300 },
			"envelope": {
				"attack": 0,
				"decay": 0.012,
				"sustain": 0,
				"release": 0.005
			},
			"gain": 0.07
		},
		"scroll": {
			"source": { "type": "sine", "frequency": 1500 },
			"envelope": {
				"attack": 0,
				"decay": 0.006,
				"sustain": 0,
				"release": 0.002
			},
			"gain": 0.04
		},
		"hover": {
			"source": { "type": "sine", "frequency": 1300 },
			"envelope": {
				"attack": 0,
				"decay": 0.008,
				"sustain": 0,
				"release": 0.003
			},
			"gain": 0.03
		},
		"toggle": {
			"source": { "type": "sine", "frequency": 1100 },
			"envelope": {
				"attack": 0,
				"decay": 0.015,
				"sustain": 0,
				"release": 0.005
			},
			"gain": 0.08
		},
		"notify": {
			"source": { "type": "sine", "frequency": 880 },
			"envelope": { "attack": 0, "decay": 0.12, "sustain": 0, "release": 0.04 },
			"gain": 0.09
		},
		"complete": {
			"source": { "type": "sine", "frequency": { "start": 880, "end": 1046 } },
			"envelope": { "attack": 0, "decay": 0.1, "sustain": 0, "release": 0.03 },
			"gain": 0.09
		},
		"loading": {
			"source": { "type": "sine", "frequency": 700 },
			"envelope": {
				"attack": 0.005,
				"decay": 0.08,
				"sustain": 0.01,
				"release": 0.03
			},
			"gain": 0.06
		},
		"tap": {
			"source": { "type": "sine", "frequency": 1400 },
			"envelope": {
				"attack": 0,
				"decay": 0.01,
				"sustain": 0,
				"release": 0.003
			},
			"gain": 0.09
		},
		"press": {
			"source": { "type": "sine", "frequency": 1200 },
			"envelope": {
				"attack": 0,
				"decay": 0.015,
				"sustain": 0,
				"release": 0.005
			},
			"gain": 0.08
		},
		"release": {
			"source": { "type": "sine", "frequency": 1000 },
			"envelope": {
				"attack": 0,
				"decay": 0.02,
				"sustain": 0,
				"release": 0.008
			},
			"gain": 0.06
		},
		"drag": {
			"source": { "type": "sine", "frequency": 900 },
			"envelope": {
				"attack": 0.003,
				"decay": 0.05,
				"sustain": 0.01,
				"release": 0.02
			},
			"gain": 0.05
		},
		"drop": {
			"source": { "type": "sine", "frequency": { "start": 900, "end": 600 } },
			"envelope": { "attack": 0, "decay": 0.06, "sustain": 0, "release": 0.02 },
			"gain": 0.07
		},
		"select": {
			"source": { "type": "sine", "frequency": 1300 },
			"envelope": {
				"attack": 0,
				"decay": 0.02,
				"sustain": 0,
				"release": 0.008
			},
			"gain": 0.08
		},
		"deselect": {
			"source": { "type": "sine", "frequency": 1100 },
			"envelope": {
				"attack": 0,
				"decay": 0.018,
				"sustain": 0,
				"release": 0.007
			},
			"gain": 0.06
		},
		"focus": {
			"source": { "type": "sine", "frequency": 1200 },
			"envelope": {
				"attack": 0,
				"decay": 0.015,
				"sustain": 0,
				"release": 0.006
			},
			"gain": 0.04
		},
		"blur": {
			"source": { "type": "sine", "frequency": 1000 },
			"envelope": {
				"attack": 0,
				"decay": 0.012,
				"sustain": 0,
				"release": 0.005
			},
			"gain": 0.03
		},
		"forward": {
			"source": { "type": "sine", "frequency": { "start": 600, "end": 800 } },
			"envelope": {
				"attack": 0,
				"decay": 0.05,
				"sustain": 0,
				"release": 0.015
			},
			"gain": 0.08
		},
		"open": {
			"source": { "type": "sine", "frequency": { "start": 500, "end": 1000 } },
			"envelope": { "attack": 0, "decay": 0.06, "sustain": 0, "release": 0.02 },
			"gain": 0.07
		},
		"close": {
			"source": { "type": "sine", "frequency": { "start": 1000, "end": 500 } },
			"envelope": { "attack": 0, "decay": 0.06, "sustain": 0, "release": 0.02 },
			"gain": 0.06
		},
		"expand": {
			"source": { "type": "sine", "frequency": { "start": 600, "end": 800 } },
			"envelope": {
				"attack": 0.003,
				"decay": 0.08,
				"sustain": 0,
				"release": 0.025
			},
			"gain": 0.06
		},
		"collapse": {
			"source": { "type": "sine", "frequency": { "start": 800, "end": 600 } },
			"envelope": {
				"attack": 0.003,
				"decay": 0.08,
				"sustain": 0,
				"release": 0.025
			},
			"gain": 0.06
		},
		"tab": {
			"source": { "type": "sine", "frequency": 1100 },
			"envelope": {
				"attack": 0,
				"decay": 0.02,
				"sustain": 0,
				"release": 0.008
			},
			"gain": 0.07
		},
		"swipe": {
			"source": { "type": "sine", "frequency": { "start": 700, "end": 1200 } },
			"envelope": {
				"attack": 0,
				"decay": 0.08,
				"sustain": 0,
				"release": 0.025
			},
			"gain": 0.06
		},
		"confirm": {
			"source": { "type": "sine", "frequency": { "start": 700, "end": 1000 } },
			"envelope": { "attack": 0, "decay": 0.06, "sustain": 0, "release": 0.02 },
			"gain": 0.09
		},
		"cancel": {
			"source": { "type": "sine", "frequency": { "start": 700, "end": 500 } },
			"envelope": { "attack": 0, "decay": 0.06, "sustain": 0, "release": 0.02 },
			"gain": 0.07
		},
		"deny": {
			"source": { "type": "sine", "frequency": { "start": 600, "end": 300 } },
			"envelope": {
				"attack": 0,
				"decay": 0.08,
				"sustain": 0,
				"release": 0.025
			},
			"gain": 0.08
		},
		"undo": {
			"source": { "type": "sine", "frequency": { "start": 900, "end": 700 } },
			"envelope": { "attack": 0, "decay": 0.06, "sustain": 0, "release": 0.02 },
			"gain": 0.07
		},
		"redo": {
			"source": { "type": "sine", "frequency": { "start": 700, "end": 900 } },
			"envelope": { "attack": 0, "decay": 0.06, "sustain": 0, "release": 0.02 },
			"gain": 0.07
		},
		"alert": {
			"source": { "type": "sine", "frequency": 880 },
			"envelope": {
				"attack": 0,
				"decay": 0.1,
				"sustain": 0.02,
				"release": 0.04
			},
			"gain": 0.1
		},
		"message": {
			"source": { "type": "sine", "frequency": 1046 },
			"envelope": {
				"attack": 0,
				"decay": 0.08,
				"sustain": 0,
				"release": 0.025
			},
			"gain": 0.08
		},
		"reminder": {
			"source": { "type": "sine", "frequency": 784 },
			"envelope": {
				"attack": 0,
				"decay": 0.12,
				"sustain": 0.02,
				"release": 0.04
			},
			"gain": 0.09
		},
		"mention": {
			"source": { "type": "sine", "frequency": 1100 },
			"envelope": { "attack": 0, "decay": 0.1, "sustain": 0, "release": 0.03 },
			"gain": 0.08
		},
		"show": {
			"source": { "type": "sine", "frequency": { "start": 600, "end": 900 } },
			"envelope": {
				"attack": 0,
				"decay": 0.05,
				"sustain": 0,
				"release": 0.015
			},
			"gain": 0.06
		},
		"hide": {
			"source": { "type": "sine", "frequency": { "start": 900, "end": 600 } },
			"envelope": {
				"attack": 0,
				"decay": 0.05,
				"sustain": 0,
				"release": 0.015
			},
			"gain": 0.05
		},
		"slide": {
			"source": { "type": "sine", "frequency": { "start": 700, "end": 1100 } },
			"envelope": {
				"attack": 0.005,
				"decay": 0.08,
				"sustain": 0,
				"release": 0.025
			},
			"gain": 0.06
		},
		"fade": {
			"source": { "type": "sine", "frequency": 800 },
			"envelope": {
				"attack": 0.01,
				"decay": 0.12,
				"sustain": 0,
				"release": 0.04
			},
			"gain": 0.05
		},
		"pop": {
			"source": { "type": "sine", "frequency": { "start": 500, "end": 200 } },
			"envelope": {
				"attack": 0,
				"decay": 0.05,
				"sustain": 0,
				"release": 0.015
			},
			"gain": 0.09
		},
		"clear": {
			"source": { "type": "sine", "frequency": { "start": 1000, "end": 600 } },
			"envelope": {
				"attack": 0,
				"decay": 0.08,
				"sustain": 0,
				"release": 0.025
			},
			"gain": 0.07
		},
		"remove": {
			"source": { "type": "sine", "frequency": { "start": 800, "end": 400 } },
			"envelope": { "attack": 0, "decay": 0.07, "sustain": 0, "release": 0.02 },
			"gain": 0.07
		},
		"trash": {
			"source": { "type": "sine", "frequency": { "start": 600, "end": 250 } },
			"envelope": { "attack": 0, "decay": 0.1, "sustain": 0, "release": 0.03 },
			"gain": 0.08
		},
		"shred": {
			"source": { "type": "sine", "frequency": { "start": 700, "end": 200 } },
			"envelope": { "attack": 0, "decay": 0.12, "sustain": 0, "release": 0.04 },
			"gain": 0.09
		},
		"upload": {
			"source": { "type": "sine", "frequency": { "start": 500, "end": 1000 } },
			"envelope": { "attack": 0, "decay": 0.1, "sustain": 0, "release": 0.03 },
			"gain": 0.08
		},
		"download": {
			"source": { "type": "sine", "frequency": { "start": 1000, "end": 500 } },
			"envelope": { "attack": 0, "decay": 0.1, "sustain": 0, "release": 0.03 },
			"gain": 0.08
		},
		"refresh": {
			"source": { "type": "sine", "frequency": { "start": 700, "end": 900 } },
			"envelope": {
				"attack": 0,
				"decay": 0.08,
				"sustain": 0,
				"release": 0.025
			},
			"gain": 0.07
		},
		"sync": {
			"source": { "type": "sine", "frequency": 880 },
			"envelope": { "attack": 0, "decay": 0.06, "sustain": 0, "release": 0.02 },
			"gain": 0.08
		},
		"process": {
			"source": { "type": "sine", "frequency": 750 },
			"envelope": {
				"attack": 0.005,
				"decay": 0.1,
				"sustain": 0.01,
				"release": 0.03
			},
			"gain": 0.06
		},
		"cut": {
			"source": { "type": "sine", "frequency": 1300 },
			"envelope": {
				"attack": 0,
				"decay": 0.01,
				"sustain": 0,
				"release": 0.004
			},
			"gain": 0.08
		},
		"snapshot": {
			"source": { "type": "sine", "frequency": 1200 },
			"envelope": {
				"attack": 0,
				"decay": 0.015,
				"sustain": 0,
				"release": 0.006
			},
			"gain": 0.09
		},
		"lock": {
			"source": { "type": "sine", "frequency": { "start": 800, "end": 600 } },
			"envelope": {
				"attack": 0,
				"decay": 0.05,
				"sustain": 0,
				"release": 0.015
			},
			"gain": 0.08
		},
		"unlock": {
			"source": { "type": "sine", "frequency": { "start": 600, "end": 900 } },
			"envelope": {
				"attack": 0,
				"decay": 0.05,
				"sustain": 0,
				"release": 0.015
			},
			"gain": 0.08
		},
		"enable": {
			"source": { "type": "sine", "frequency": { "start": 700, "end": 1000 } },
			"envelope": { "attack": 0, "decay": 0.06, "sustain": 0, "release": 0.02 },
			"gain": 0.07
		},
		"disable": {
			"source": { "type": "sine", "frequency": { "start": 1000, "end": 700 } },
			"envelope": { "attack": 0, "decay": 0.06, "sustain": 0, "release": 0.02 },
			"gain": 0.06
		},
		"connect": {
			"source": { "type": "sine", "frequency": { "start": 600, "end": 1100 } },
			"envelope": {
				"attack": 0,
				"decay": 0.08,
				"sustain": 0,
				"release": 0.025
			},
			"gain": 0.08
		},
		"disconnect": {
			"source": { "type": "sine", "frequency": { "start": 1100, "end": 600 } },
			"envelope": {
				"attack": 0,
				"decay": 0.08,
				"sustain": 0,
				"release": 0.025
			},
			"gain": 0.07
		},
		"mute": {
			"source": { "type": "sine", "frequency": { "start": 900, "end": 500 } },
			"envelope": { "attack": 0, "decay": 0.06, "sustain": 0, "release": 0.02 },
			"gain": 0.07
		},
		"unmute": {
			"source": { "type": "sine", "frequency": { "start": 500, "end": 900 } },
			"envelope": { "attack": 0, "decay": 0.06, "sustain": 0, "release": 0.02 },
			"gain": 0.08
		},
		"record": {
			"source": { "type": "sine", "frequency": 660 },
			"envelope": {
				"attack": 0.005,
				"decay": 0.08,
				"sustain": 0.02,
				"release": 0.03
			},
			"gain": 0.08
		},
		"capture": {
			"source": { "type": "sine", "frequency": 1100 },
			"envelope": {
				"attack": 0,
				"decay": 0.02,
				"sustain": 0,
				"release": 0.008
			},
			"gain": 0.09
		}
	}
}
